bucky/__init__.py
bucky/carbon.py
bucky/cfg.py
bucky/client.py
bucky/collectd.py
bucky/errors.py
bucky/helpers.py
bucky/main.py
bucky/metricsd.py
bucky/names.py
bucky/processor.py
bucky/sentry.py
bucky/statsd.py
bucky/udpserver.py
bucky/metrics/__init__.py
bucky/metrics/counter.py
bucky/metrics/gauge.py
bucky/metrics/histogram.py
bucky/metrics/meter.py
bucky/metrics/metric.py
bucky/metrics/timer.py
bucky/metrics/stats/__init__.py
bucky/metrics/stats/ewma.py
bucky/metrics/stats/expdec_sample.py
bucky/metrics/stats/usample.py
bucky-2.3.0.dist-info/DESCRIPTION.rst
bucky-2.3.0.dist-info/entry_points.txt
bucky-2.3.0.dist-info/METADATA
bucky-2.3.0.dist-info/metadata.json
bucky-2.3.0.dist-info/pbr.json
bucky-2.3.0.dist-info/RECORD
bucky-2.3.0.dist-info/top_level.txt
bucky-2.3.0.dist-info/WHEEL
