Metadata-Version: 2.0
Name: bucky
Version: 2.3.0
Summary: StatsD and CollectD adapter for Graphite
Home-page: http://github.com/trbs/bucky.git
Author: Trbs
Author-email: trbs@trbs.net
License: ASF2.0
Platform: UNKNOWN
Classifier: Development Status :: 4 - Beta
Classifier: Environment :: Other Environment
Classifier: Intended Audience :: Developers
Classifier: Intended Audience :: System Administrators
Classifier: Intended Audience :: Information Technology
Classifier: License :: OSI Approved :: Apache Software License
Classifier: Operating System :: MacOS :: MacOS X
Classifier: Operating System :: POSIX
Classifier: Operating System :: POSIX :: Linux
Classifier: Operating System :: POSIX :: BSD
Classifier: Operating System :: Unix
Classifier: Programming Language :: Python
Classifier: Programming Language :: Python :: 2
Classifier: Programming Language :: Python :: 3
Classifier: Topic :: Internet :: Log Analysis
Classifier: Topic :: System :: Networking :: Monitoring
Classifier: Topic :: Utilities
Requires-Dist: six
Requires-Dist: setproctitle
Requires-Dist: pycrypto
Requires-Dist: watchdog
